LICENSE
MANIFEST.in
README.md
setup.py
tox.ini
swing_server/__init__.py
swing_server/api.py
swing_server/app.py
swing_server/auth.py
swing_server/chart.py
swing_server/config.py
swing_server/errors.py
swing_server/helpers.py
swing_server/models.py
swing_server/storage.py
swing_server.egg-info/PKG-INFO
swing_server.egg-info/SOURCES.txt
swing_server.egg-info/dependency_links.txt
swing_server.egg-info/not-zip-safe
swing_server.egg-info/requires.txt
swing_server.egg-info/top_level.txt