Metadata-Version: 2.1
Name: swing-server
Version: 0.2
Summary: An open-source Swing chart repository server
Home-page: https://github.com/docker-swing/swing-server
Author: Jan Šafařík
Author-email: cowjen01@gmail.com
License: Apache License 2.0
Keywords: docker,swarm,repository
Platform: UNKNOWN
Classifier: Framework :: Flask
Classifier: Environment :: Web Environment
Classifier: Intended Audience :: Developers
Classifier: License :: OSI Approved :: Apache Software License
Classifier: Operating System :: POSIX :: Linux
Classifier: Operating System :: MacOS
Classifier: Programming Language :: Python
Classifier: Programming Language :: Python :: 3
Classifier: Programming Language :: Python :: 3.6
Classifier: Programming Language :: Python :: 3.7
